oarepo_model_builder/__init__.py
oarepo_model_builder/builder.py
oarepo_model_builder/cli.py
oarepo_model_builder/entrypoints.py
oarepo_model_builder/exceptions.py
oarepo_model_builder/fs.py
oarepo_model_builder/generate_doc.py
oarepo_model_builder/merger.py
oarepo_model_builder/schema.py
oarepo_model_builder/builders/__init__.py
oarepo_model_builder/builders/json_base.py
oarepo_model_builder/builders/jsonschema.py
oarepo_model_builder/builders/mapping.py
oarepo_model_builder/builders/model_saver.py
oarepo_model_builder/builders/pyproject_toml.py
oarepo_model_builder/builders/python.py
oarepo_model_builder/builders/python_structure.py
oarepo_model_builder/builders/setup_cfg.py
oarepo_model_builder/builders/setup_py.py
oarepo_model_builder/builders/utils.py
oarepo_model_builder/builders/templates/__init__.py
oarepo_model_builder/builders/templates/setup.py.jinja2
oarepo_model_builder/builtin_models/__init__.py
oarepo_model_builder/builtin_models/doi.json
oarepo_model_builder/builtin_models/invenio.json
oarepo_model_builder/builtin_models/oaipmh.json
oarepo_model_builder/datatypes/__init__.py
oarepo_model_builder/datatypes/datatypes.py
oarepo_model_builder/datatypes/dates.py
oarepo_model_builder/datatypes/model.py
oarepo_model_builder/datatypes/primitive_types.py
oarepo_model_builder/datatypes/strings.py
oarepo_model_builder/datatypes/components/__init__.py
oarepo_model_builder/datatypes/components/enum.py
oarepo_model_builder/datatypes/components/sample.py
oarepo_model_builder/datatypes/components/ui.py
oarepo_model_builder/datatypes/components/facets/__init__.py
oarepo_model_builder/datatypes/components/facets/array.py
oarepo_model_builder/datatypes/components/facets/field.py
oarepo_model_builder/datatypes/components/facets/nested.py
oarepo_model_builder/datatypes/components/facets/object.py
oarepo_model_builder/datatypes/components/marshmallow/__init__.py
oarepo_model_builder/datatypes/components/marshmallow/array.py
oarepo_model_builder-4.1.1.dist-info/licenses/LICENSE
oarepo_model_builder-4.1.1.dist-info/METADATA
oarepo_model_builder-4.1.1.dist-info/WHEEL
oarepo_model_builder-4.1.1.dist-info/entry_points.txt
oarepo_model_builder-4.1.1.dist-info/top_level.txt
oarepo_model_builder-4.1.1.dist-info/RECORD
