Metadata-Version: 2.4
Name: oarepo-model-builder
Version: 4.1.1
Summary: A utility library that generates OARepo required data model files from a JSON specification file
License-File: LICENSE
Requires-Dist: ConfigUpdater<4.0.0,>=3.1.1
Requires-Dist: Faker>11.3.0
Requires-Dist: Jinja2<4.0.0,>=3.0.3
Requires-Dist: PyYAML<7.0,>=6.0
Requires-Dist: black>23
Requires-Dist: click>=7.1
Requires-Dist: deepdiff<6.0.0,>=5.6.0
Requires-Dist: isort<6.0.0,>=5.10.1
Requires-Dist: json5<0.10.0,>=0.9.6
Requires-Dist: jsonpointer<3.0,>=2.2
Requires-Dist: lazy-object-proxy<2.0.0,>=1.7.1
Requires-Dist: libcst>=0.3.19
Requires-Dist: tomlkit>=0.7.2
Requires-Dist: importlib_metadata>=4.0.0
Requires-Dist: marshmallow<4.0.0,>=3.22.0
Requires-Dist: marshmallow-union
Requires-Dist: marshmallow-oneofschema
Requires-Dist: autoflake
Requires-Dist: frozendict
Provides-Extra: devs
Requires-Dist: pytest>=7.1.2; extra == "devs"
Requires-Dist: black; extra == "devs"
Requires-Dist: isort; extra == "devs"
Provides-Extra: tests
Requires-Dist: pytest>=7.1.2; extra == "tests"
Dynamic: license-file
